setup.py
cryptocurrency_cli_tools.egg-info/PKG-INFO
cryptocurrency_cli_tools.egg-info/SOURCES.txt
cryptocurrency_cli_tools.egg-info/dependency_links.txt
cryptocurrency_cli_tools.egg-info/entry_points.txt
cryptocurrency_cli_tools.egg-info/requires.txt
cryptocurrency_cli_tools.egg-info/top_level.txt
cryptocurrency_cli_tools/runnable/__init__.py
cryptocurrency_cli_tools/runnable/bip39gen.py